README.rst
setup.cfg
setup.py
meta_tests/__init__.py
nose_enhanced_descriptions/__init__.py
nose_enhanced_descriptions.egg-info/PKG-INFO
nose_enhanced_descriptions.egg-info/SOURCES.txt
nose_enhanced_descriptions.egg-info/dependency_links.txt
nose_enhanced_descriptions.egg-info/entry_points.txt
nose_enhanced_descriptions.egg-info/requires.txt
nose_enhanced_descriptions.egg-info/top_level.txt