Metadata-Version: 1.1
Name: nose-enhanced-descriptions
Version: 0.1.5
Summary: Improves nose test description output
Home-page: https://github.com/paul-butcher/nose_enhanced_descriptions
Author: Paul Butcher
Author-email: paul.butcher@gmail.com
License: UNKNOWN
Platform: UNKNOWN
Classifier: Development Status :: 4 - Beta
Classifier: Programming Language :: Python
Classifier: Programming Language :: Python :: 2
Classifier: Programming Language :: Python :: 2.7
Classifier: Programming Language :: Python :: 3
Classifier: Programming Language :: Python :: 3.4
Classifier: Programming Language :: Python :: 3.5
Classifier: Topic :: Software Development :: Testing
Classifier: License :: OSI Approved :: MIT License
